openi/__init__.py
openi/apis.py
openi/cli.py
openi/login.py
openi/settings.py
openi/dataset/__init__.py
openi/dataset/dataset_file.py
openi/dataset/download.py
openi/dataset/upload.py
openi/utils/__init__.py
openi/utils/file_utils.py
openi/utils/logger.py
openi_dev-0.0.1.dist-info/METADATA
openi_dev-0.0.1.dist-info/WHEEL
openi_dev-0.0.1.dist-info/entry_points.txt
openi_dev-0.0.1.dist-info/top_level.txt
openi_dev-0.0.1.dist-info/RECORD
